pollux_model/__init__.py
pollux_model/adder/adder.py
pollux_model/compressor/compressor.py
pollux_model/electrolyser/electrolyser_physics_based.py
pollux_model/electrolyser/electrolyser_physics_based_with_compressor.py
pollux_model/gas_storage/hydrogen_tank_model.py
pollux_model/heat_demand/heat_demand_profiles.py
pollux_model/heat_pump/__init__.py
pollux_model/heat_pump/heat_pump_physics_based.py
pollux_model/heat_pump/NREL_components/__init__.py
pollux_model/heat_pump/NREL_components/heat_pump_model.py
pollux_model/heat_pump/NREL_components/heat_pump_model_inputs.yml
pollux_model/heat_pump/NREL_components/utilities/__init__.py
pollux_model/heat_pump/NREL_components/utilities/libraries.py
pollux_model/heat_pump/NREL_components/utilities/refrigerant_properties.py
pollux_model/heat_pump/NREL_components/utilities/unit_defs.py
pollux_model/heat_pump/NREL_components/utilities/visualization.ipynb
pollux_model/heat_storage/__init__.py
pollux_model/heat_storage/water_buffer.py
pollux_model/hydrogen_demand/hydrogen_demand_profiles.py
pollux_model/model_abstract.py
pollux_model/model_example/model_example.py
pollux_model/power_demand/power_demand_profiles.py
pollux_model/power_supply/power_supply_profiles.py
pollux_model/solver/key_performance_indicators.py
pollux_model/solver/solver.py
pollux_model/solver/step_function.py
pollux_model/splitter/splitter.py
pollux_model-0.2.1.dist-info/LICENSE
pollux_model-0.2.1.dist-info/METADATA
pollux_model-0.2.1.dist-info/WHEEL
pollux_model-0.2.1.dist-info/RECORD
