Metadata-Version: 2.1
Name: pollux-model
Version: 0.2.1
Summary: Core model library of the POLLUX Digital Twin
Home-page: https://tno.nl
Author: Demetris Palochis
Author-email: demetris.palochis@tno.nl
Requires-Python: >=3.11,<4.0
Classifier: Development Status :: 3 - Alpha
Classifier: Intended Audience :: Developers
Classifier: Intended Audience :: Information Technology
Classifier: Intended Audience :: Science/Research
Classifier: License :: OSI Approved :: GNU General Public License v3 (GPLv3)
Classifier: Operating System :: OS Independent
Classifier: Programming Language :: Python :: 3
Classifier: Programming Language :: Python :: 3.11
Classifier: Programming Language :: Python :: 3.12
Classifier: Topic :: Scientific/Engineering
Classifier: Topic :: Scientific/Engineering :: Mathematics
Classifier: Topic :: Scientific/Engineering :: Physics
Requires-Dist: CoolProp (>=6.6.0,<7.0.0)
Requires-Dist: flake8 (>=7.0.0,<8.0.0)
Requires-Dist: matplotlib (>=3.9.2,<4.0.0)
Requires-Dist: numpy (>=1.26.4,<2.0.0)
Requires-Dist: numpy-financial (>=1.0.0,<2.0.0)
Requires-Dist: pandas (>=2.2.2,<3.0.0)
Requires-Dist: pint (>=0.24.3,<0.25.0)
Requires-Dist: plotly (>=5.24.0,<6.0.0)
Requires-Dist: pyaml (>=24.7.0,<25.0.0)
Requires-Dist: pyjnius (>=1.6.1,<2.0.0)
Requires-Dist: pytest (>=8.2.2,<9.0.0)
Requires-Dist: pytest-cov (>=5.0.0,<6.0.0)
Requires-Dist: scipy (==1.13.1)
Requires-Dist: thermo (>=0.3.0,<0.4.0)
Project-URL: Documentation, https://readthedocs.org
Project-URL: Repository, https://github.com/Pollux-digital-twin/pollux-model
